sayou/brain/__init__.py
sayou/brain/core/config.py
sayou/brain/core/exceptions.py
sayou/brain/pipelines/standard.py
sayou/brain/pipelines/transfer.py
sayou_brain-0.3.4.dist-info/METADATA
sayou_brain-0.3.4.dist-info/WHEEL
sayou_brain-0.3.4.dist-info/RECORD
