Metadata-Version: 2.4
Name: sayou-brain
Version: 0.3.4
Summary: Brain components for the Sayou Data Platform
Project-URL: Homepage, https://www.sayouzone.com/
Project-URL: Documentation, https://sayouzone.github.io/sayou-fabric/
Project-URL: Repository, https://github.com/sayouzone/sayou-fabric
Author-email: Sayouzone <contact@sayouzone.com>
License:                                  Apache License
Classifier: License :: OSI Approved :: Apache Software License
Classifier: Operating System :: OS Independent
Classifier: Programming Language :: Python :: 3.9
Classifier: Programming Language :: Python :: 3.10
Classifier: Programming Language :: Python :: 3.11
Classifier: Topic :: Software Development :: Libraries :: Application Frameworks
Requires-Python: >=3.9
Requires-Dist: sayou-assembler~=0.3.2
Requires-Dist: sayou-chunking~=0.3.2
Requires-Dist: sayou-connector~=0.3.5
Requires-Dist: sayou-core==0.3.0
Requires-Dist: sayou-document~=0.3.2
Requires-Dist: sayou-loader~=0.3.4
Requires-Dist: sayou-refinery~=0.3.3
Requires-Dist: sayou-wrapper~=0.3.2
